iflow_mcp_proxmox_mcp-0.1.0.dist-info/licenses/LICENSE
proxmox_mcp/__init__.py
proxmox_mcp/server.py
proxmox_mcp/config/__init__.py
proxmox_mcp/config/loader.py
proxmox_mcp/config/models.py
proxmox_mcp/core/__init__.py
proxmox_mcp/core/logging.py
proxmox_mcp/core/proxmox.py
proxmox_mcp/formatting/__init__.py
proxmox_mcp/formatting/colors.py
proxmox_mcp/formatting/components.py
proxmox_mcp/formatting/formatters.py
proxmox_mcp/formatting/templates.py
proxmox_mcp/formatting/theme.py
proxmox_mcp/tools/__init__.py
proxmox_mcp/tools/base.py
proxmox_mcp/tools/cluster.py
proxmox_mcp/tools/definitions.py
proxmox_mcp/tools/node.py
proxmox_mcp/tools/storage.py
proxmox_mcp/tools/vm.py
proxmox_mcp/tools/console/__init__.py
proxmox_mcp/tools/console/manager.py
proxmox_mcp/utils/__init__.py
proxmox_mcp/utils/auth.py
proxmox_mcp/utils/logging.py
iflow_mcp_proxmox_mcp-0.1.0.dist-info/METADATA
iflow_mcp_proxmox_mcp-0.1.0.dist-info/WHEEL
iflow_mcp_proxmox_mcp-0.1.0.dist-info/entry_points.txt
iflow_mcp_proxmox_mcp-0.1.0.dist-info/top_level.txt
iflow_mcp_proxmox_mcp-0.1.0.dist-info/RECORD
