Metadata-Version: 2.4
Name: iflow-mcp_proxmox-mcp
Version: 0.1.0
Summary: A Model Context Protocol server for interacting with Proxmox hypervisors
Author: Kevin
Author-email: Kevin <kevin@example.com>
License: MIT
Project-URL: Homepage, https://github.com/yourusername/proxmox-mcp
Project-URL: Documentation, https://github.com/yourusername/proxmox-mcp#readme
Project-URL: Repository, https://github.com/yourusername/proxmox-mcp.git
Project-URL: Issues, https://github.com/yourusername/proxmox-mcp/issues
Keywords: proxmox,mcp,virtualization,cline,qemu,lxc
Classifier: Development Status :: 3 - Alpha
Classifier: Intended Audience :: Developers
Classifier: License :: OSI Approved :: MIT License
Classifier: Programming Language :: Python :: 3
Classifier: Programming Language :: Python :: 3.9
Classifier: Programming Language :: Python :: 3.10
Classifier: Programming Language :: Python :: 3.11
Classifier: Programming Language :: Python :: 3.12
Classifier: Topic :: Software Development :: Libraries :: Python Modules
Classifier: Topic :: System :: Systems Administration
Requires-Python: >=3.9
License-File: LICENSE
Requires-Dist: mcp[cli]
Requires-Dist: proxmoxer<3.0.0,>=2.0.1
Requires-Dist: requests<3.0.0,>=2.31.0
Requires-Dist: pydantic<3.0.0,>=2.0.0
Provides-Extra: dev
Requires-Dist: pytest<8.0.0,>=7.0.0; extra == "dev"
Requires-Dist: black<24.0.0,>=23.0.0; extra == "dev"
Requires-Dist: mypy<2.0.0,>=1.0.0; extra == "dev"
Requires-Dist: pytest-asyncio<0.22.0,>=0.21.0; extra == "dev"
Requires-Dist: ruff<0.2.0,>=0.1.0; extra == "dev"
Requires-Dist: types-requests<3.0.0,>=2.31.0; extra == "dev"
Dynamic: author
Dynamic: license-file
Dynamic: requires-python
